bsu/__init__.py
bsu/bsu.py
bsu/cli.py
bsu/constants.py
bsu/lang.py
bsu/parser.py
bsu/uploader.py
bsu/youtube_subtitle.py
bsu-0.0.1.dist-info/METADATA
bsu-0.0.1.dist-info/WHEEL
bsu-0.0.1.dist-info/entry_points.txt
bsu-0.0.1.dist-info/top_level.txt
bsu-0.0.1.dist-info/RECORD
