Metadata-Version: 2.4
Name: bsu
Version: 0.0.1
Summary: B站字幕批量上传工具
Requires-Python: >=3.11
Requires-Dist: aiohttp>=3.12.15
Requires-Dist: bilibili-api-python>=17.3.0
Requires-Dist: bs4>=0.0.2
Requires-Dist: click>=8.2.1
Requires-Dist: pysubs2>=1.8.0
Requires-Dist: pytube>=15.0.0
Requires-Dist: requests>=2.32.4
Requires-Dist: youtube-transcript-api>=1.2.1
